pysparkparquethelper/__init__.py
pysparkparquethelper/pysparkparquethelper.py
pysparkparquethelper-0.0.4.dist-info/METADATA
pysparkparquethelper-0.0.4.dist-info/WHEEL
pysparkparquethelper-0.0.4.dist-info/top_level.txt
pysparkparquethelper-0.0.4.dist-info/RECORD
