Metadata-Version: 2.1
Name: pysparkparquethelper
Version: 0.0.4
Requires-Dist: logclshelper
Requires-Dist: pysparkhelper
Requires-Dist: pysparkhdfshelper
